{"cameraMode":{"drawMode":0,"name":"Shaded","section":"Shading Mode"},"sceneLighting":true,"audioPlay":false,"sceneViewState":{"m_AlwaysRefresh":false,"showFog":true,"showSkybox":true,"showFlares":true,"showImageEffects":true,"showParticleSystems":true,"showVisualEffectGraphs":true,"m_FxEnabled":true},"in2DMode":false,"pivot":{"x":-36.79658508300781,"y":-16.014944076538087,"z":-27.885940551757814},"rotation":{"x":0.24547801911830903,"y":-0.5075601935386658,"z":0.15455487370491029,"w":0.81131911277771},"size":16.98845863342285,"orthographic":false}